PyTgram_bot/__init__.py
PyTgram_bot/dispatcher.py
PyTgram_bot/handler.py
PyTgram_bot/message_types.py
PyTgram_bot/tempCodeRunnerFile.py
PyTgram_bot/updater.py
nt_pytgram_bot-0.1.0.dist-info/licenses/LICENSE
nt_pytgram_bot-0.1.0.dist-info/METADATA
nt_pytgram_bot-0.1.0.dist-info/WHEEL
nt_pytgram_bot-0.1.0.dist-info/top_level.txt
nt_pytgram_bot-0.1.0.dist-info/RECORD
