Metadata-Version: 2.4
Name: nt_PyTgram_bot
Version: 0.1.0
Summary: Python Telegram Bot
Home-page: https://github.com/sevapova/py-gram-bot/PyTgram_bot
Author: Latipova Sevara
Classifier: Programming Language :: Python
Classifier: License :: OSI Approved :: MIT License
Classifier: Operating System :: OS Independent
Requires-Python: >=3.11
License-File: LICENSE
Dynamic: author
Dynamic: classifier
Dynamic: description
Dynamic: description-content-type
Dynamic: home-page
Dynamic: license-file
Dynamic: requires-python
Dynamic: summary
